LICENSE
MANIFEST.in
README.rst
setup.py
IsobarImg/IsobarImg.py
IsobarImg/__init__.py
IsobarImg.egg-info/PKG-INFO
IsobarImg.egg-info/SOURCES.txt
IsobarImg.egg-info/dependency_links.txt
IsobarImg.egg-info/not-zip-safe
IsobarImg.egg-info/requires.txt
IsobarImg.egg-info/top_level.txt