Metadata-Version: 1.0
Name: IsobarImg
Version: 0.4.0
Summary: isobar python image library
Home-page: https://github.com/wwwins/IsobarImgPy
Author: wwwins
Author-email: cphuang72@gmail.com
License: MIT
Keywords: IsobarImg
Platform: UNKNOWN
